pypi_dist.py
pypi_dist-0.1.1.dist-info/LICENSE
pypi_dist-0.1.1.dist-info/METADATA
pypi_dist-0.1.1.dist-info/WHEEL
pypi_dist-0.1.1.dist-info/entry_points.txt
pypi_dist-0.1.1.dist-info/top_level.txt
pypi_dist-0.1.1.dist-info/RECORD
